provisioner_single_board_plugin/main.py
provisioner_single_board_plugin/main_dev.py
provisioner_single_board_plugin/main_fake.py
provisioner_single_board_plugin/resources/__init__.py
provisioner_single_board_plugin/resources/config.yaml
provisioner_single_board_plugin/resources/version.txt
provisioner_single_board_plugin/src/common/remote/remote_network_configure.py
provisioner_single_board_plugin/src/common/remote/remote_network_configure_test.py
provisioner_single_board_plugin/src/common/remote/remote_os_configure.py
provisioner_single_board_plugin/src/common/remote/remote_os_configure_test.py
provisioner_single_board_plugin/src/config/domain/config.py
provisioner_single_board_plugin/src/config/domain/config_fakes.py
provisioner_single_board_plugin/src/config/domain/config_test.py
provisioner_single_board_plugin/src/raspberry_pi/__init__.py
provisioner_single_board_plugin/src/raspberry_pi/cli.py
provisioner_single_board_plugin/src/raspberry_pi/node/__init__.py
provisioner_single_board_plugin/src/raspberry_pi/node/cli.py
provisioner_single_board_plugin/src/raspberry_pi/node/cli_test.py
provisioner_single_board_plugin/src/raspberry_pi/node/configure_cmd.py
provisioner_single_board_plugin/src/raspberry_pi/node/configure_cmd_test.py
provisioner_single_board_plugin/src/raspberry_pi/node/network_cmd.py
provisioner_single_board_plugin/src/raspberry_pi/node/network_cmd_test.py
provisioner_single_board_plugin/src/raspberry_pi/os/__init__.py
provisioner_single_board_plugin/src/raspberry_pi/os/burn_image_cmd.py
provisioner_single_board_plugin/src/raspberry_pi/os/burn_image_cmd_test.py
provisioner_single_board_plugin/src/raspberry_pi/os/cli.py
provisioner_single_board_plugin/src/raspberry_pi/os/cli_test.py
provisioner_single_board_plugin-0.1.5.dist-info/METADATA
provisioner_single_board_plugin-0.1.5.dist-info/WHEEL
provisioner_single_board_plugin-0.1.5.dist-info/entry_points.txt
provisioner_single_board_plugin-0.1.5.dist-info/RECORD
